fxutil/__init__.py
fxutil/cli.py
fxutil/common.py
fxutil/file_helpers.py
fxutil/manuscript.py
fxutil/meta.py
fxutil/plotting.py
fxutil/typing.py
fxutil/imports/__init__.py
fxutil/imports/general.py
fxutil/mplstyles/__init__.py
fxutil/mplstyles/dark.mplstyle
fxutil/mplstyles/light.mplstyle
fxutil/mplstyles/tex.mplstyle
fxutil-2.0.1.post13.dist-info/licenses/LICENSE
fxutil-2.0.1.post13.dist-info/METADATA
fxutil-2.0.1.post13.dist-info/WHEEL
fxutil-2.0.1.post13.dist-info/entry_points.txt
fxutil-2.0.1.post13.dist-info/top_level.txt
fxutil-2.0.1.post13.dist-info/RECORD
