Metadata-Version: 2.4
Name: fxutil
Version: 2.0.1.post13
Summary: Some handy tools...
Author-email: Felix Jung <felix.jung@tu-dresden.de>
License-Expression: MIT
Project-URL: Repository, https://github.com/fxjung/fxutil
Keywords: utilities,python,science
Classifier: Intended Audience :: Science/Research
Classifier: Natural Language :: English
Classifier: Programming Language :: Python :: 3.10
Classifier: Topic :: Scientific/Engineering :: Physics
Requires-Python: >=3.10
License-File: LICENSE
Requires-Dist: pytest
Requires-Dist: pre-commit
Requires-Dist: matplotlib
Requires-Dist: h5py
Requires-Dist: tables
Requires-Dist: scipy
Requires-Dist: numpy
Requires-Dist: pandas
Requires-Dist: networkx
Requires-Dist: seaborn
Requires-Dist: pympler
Requires-Dist: pygit2
Requires-Dist: typer
Requires-Dist: ipython>=8.37.0
Provides-Extra: dev
Requires-Dist: black==24.8.0; extra == "dev"
Requires-Dist: flake8; extra == "dev"
Requires-Dist: pytest; extra == "dev"
Dynamic: license-file
